fonts/D-DINCondensed-Bold.otf
fonts/D-DINCondensed.otf
fonts/D-DINExp.otf
fonts/ddin-bold.otf
fonts/ddin-bold_italic.otf
fonts/ddin-italic.otf
fonts/ddin-normal.otf
lv_doc_tools/RSLogo.png
lv_doc_tools/RS_theme.yml
lv_doc_tools/__init__.py
lv_doc_tools/caraya_parser.py
lv_doc_tools/caraya_runner.py
lv_doc_tools/cleaner.py
lv_doc_tools/cli.py
lv_doc_tools/config_loader.py
lv_doc_tools/gaphor_runner.py
lv_doc_tools/generator.py
lv_doc_tools/publisher.py
lv_doc_tools/verifybranch.py
lv_doc_tools-2.3.0.dist-info/licenses/LICENSE.txt
lv_doc_tools-2.3.0.dist-info/METADATA
lv_doc_tools-2.3.0.dist-info/WHEEL
lv_doc_tools-2.3.0.dist-info/entry_points.txt
lv_doc_tools-2.3.0.dist-info/top_level.txt
lv_doc_tools-2.3.0.dist-info/RECORD
