Metadata-Version: 2.4
Name: lv_doc_tools
Version: 2.3.0
Summary: Tool for generating documentation of LabView projects.
Home-page: https://github.com/pyscaffold/pyscaffold/
Author: Mike Kidner
Author-email: Mike Kidner <mike.kidner@resonatesystems.coma.u>
License: MIT
Platform: any
Classifier: Programming Language :: Python :: 3
Classifier: License :: OSI Approved :: MIT License
Classifier: Operating System :: OS Independent
Requires-Python: >=3.7
License-File: LICENSE.txt
Dynamic: license-file
